poziq/__init__.py
poziq/cli.py
poziq/encoder.py
poziq/image.py
poziq/utils.py
tests/__init__.py
tests/fixtures.py
tests/test_cli.py
tests/test_encoder.py
tests/test_image.py
poziq-0.1.0.dist-info/LICENSE
poziq-0.1.0.dist-info/METADATA
poziq-0.1.0.dist-info/WHEEL
poziq-0.1.0.dist-info/entry_points.txt
poziq-0.1.0.dist-info/top_level.txt
poziq-0.1.0.dist-info/RECORD
