Metadata-Version: 2.1
Name: poziq
Version: 0.1.0
Summary: A tool for slicing, encoding, and assembling images
Home-page: https://github.com/mitzakee/poziq
Author: Radu Coanda
Author-email: me@coanda.xyz
Classifier: Development Status :: 3 - Alpha
Classifier: Intended Audience :: Education
Classifier: License :: OSI Approved :: MIT License
Classifier: Operating System :: OS Independent
Classifier: Programming Language :: Python :: 3
Classifier: Programming Language :: Python :: 3.8
Classifier: Programming Language :: Python :: 3.9
Classifier: Programming Language :: Python :: 3.10
Classifier: Programming Language :: Python :: 3.11
Requires-Python: >=3.9
License-File: LICENSE
Requires-Dist: click==8.1.7
Requires-Dist: Pillow==11.0.0
Provides-Extra: dev
Requires-Dist: pytest==8.3.4; extra == "dev"
Requires-Dist: pytest-cov==6.0.0; extra == "dev"
Requires-Dist: black; extra == "dev"
Requires-Dist: isort; extra == "dev"
